pexels_lib/client.py
pexels_lib/models/photo.py
pexels_lib/utils/downloader.py
pexels_lib-1.0.0.dist-info/METADATA
pexels_lib-1.0.0.dist-info/WHEEL
pexels_lib-1.0.0.dist-info/top_level.txt
pexels_lib-1.0.0.dist-info/RECORD
