Metadata-Version: 2.4
Name: pexels-lib
Version: 1.0.0
Summary: Simple Pexels Libray to get photos
Author: Aluzay
Project-URL: Homepage, https://github.com/Aluzay/PexelsLib
Classifier: Programming Language :: Python :: 3
Classifier: License :: OSI Approved :: MIT License
Requires-Python: >=3.10
